content_alchemist/__init__.py
content_alchemist/hello.py
content_alchemist/stremapp.py
content_alchemist-0.0.2.dist-info/METADATA
content_alchemist-0.0.2.dist-info/WHEEL
content_alchemist-0.0.2.dist-info/RECORD
